repo2file4gpt/__init__.py
repo2file4gpt/__main__.py
repo2file4gpt/config.py
repo2file4gpt/gh_api_wrapper.py
repo2file4gpt/markdown_exporter.py
repo2file4gpt/repo_scrapper.py
tests/__init__.py
tests/test_main.py
repo2file4gpt-0.1.0.dist-info/METADATA
repo2file4gpt-0.1.0.dist-info/WHEEL
repo2file4gpt-0.1.0.dist-info/top_level.txt
repo2file4gpt-0.1.0.dist-info/RECORD
