Metadata-Version: 2.1
Name: repo2file4gpt
Version: 0.1.0
Requires-Dist: PyGithub
Requires-Dist: tqdm
